{
	" 집에 잘 도착했습니다 ㅎㅎ": " 으으 어지러워ㅠㅠ",
	" 으으 어지러워ㅠㅠ": " 오늘도 쉅있다고하지 않았음?ㅋㅋ",
	" 오늘도 쉅있다고하지 않았음?ㅋㅋ": " ㅎㅎㅎㅎ 네 못갔습니다^^",
	" ㅎㅎㅎㅎ 네 못갔습니다^^": " ㅋㅋㅋㅋㅋㅋㅋㅋㅋㅋ",
	" ㅋㅋㅋㅋㅋㅋㅋㅋㅋㅋ": " (굿)",
	" (굿)": " ㅋㅋㅋㅋㅋㅋ근데 저도 강화학습 잘몰라여.....ㅎㅎㅎ",
	" 어제 많이 취햇었나봐요 저": " 언제 산건지도 모르겟어요 ㅋㅋㅋㅋ",
	" 언제 산건지도 모르겟어요 ㅋㅋㅋㅋ": " 엥ㅋㅋㅋ",
	" 엥ㅋㅋㅋ": " 2차 끝나구 나오자마자 택시타구 가지않았었냐ㅋㅋㅋ",
	" 2차 끝나구 나오자마자 택시타구 가지않았었냐ㅋㅋㅋ": " ㅋㅋㅋㅋㅋㅋ 그쵸",
	" ㅋㅋㅋㅋㅋㅋ 그쵸": " 택시타고 집앞에 내렸던건 기억나는데",
	" 택시타고 집앞에 내렸던건 기억나는데": " 그 이후로 아침이에요 그냥 ㅋㅋㅋ",
	" 그 이후로 아침이에요 그냥 ㅋㅋㅋ": " 어제 많이 마셨나보넹ㅋㅋ",
	" 어제 많이 마셨나보넹ㅋㅋ": " 푹쉬어유~~",
	" 푹쉬어유~~": " ㅋㅋㅋ 알겠습니당",
	" ㅋㅋㅋ 알겠습니당": " 못찾겠다",
	" 못찾겠다": " 꾀꼬리",
	" 꾀꼬리": "//stackoverflow.com/questions/6040583/cant-find-the-libpq-fe-h-header-when-trying-to-install-pg-gem",
	"//stackoverflow.com/questions/6040583/cant-find-the-libpq-fe-h-header-when-trying-to-install-pg-gem": " 보이스톡 해요",
	" 보이스톡 해요": "34",
	"25": " 혁렬아 애지문쪽 국제학부 주점으루",
	" 혁렬아 애지문쪽 국제학부 주점으루": " 음",
	" 음": " 정확히 어디에요?",
	" 정확히 어디에요?": " 2번출구쪽ㅋㅋ",
	" 2번출구쪽ㅋㅋ": " 지금 애지문",
	" 지금 애지문": " 앞이에요 ㅋㅋㅋ",
	" 앞이에요 ㅋㅋㅋ": " 보이스톡 해요",
	" 응답 없음": " 보이스톡 해요",
	"39": " 형!",
	" 형!": " 저 티셔츠 m사이즈 신청할게요!",
	" 저 티셔츠 m사이즈 신청할게요!": " 입금 지금 하겟씁니다. 늦어서 죄송해요~",
	" 입금 지금 하겟씁니다. 늦어서 죄송해요~": " 민성이형한테 하라니께ㅋㅋㅋ",
	" 민성이형한테 하라니께ㅋㅋㅋ": " 아.. 잘못봤어요 ㅎㅎ",
	" 아.. 잘못봤어요 ㅎㅎ": " (이모티콘) 죄송합니다~",
	" (이모티콘) 죄송합니다~": " ㅋㅋㅋㅋㅋ",
	" ㅋㅋㅋㅋㅋ": " ㅋㅋㅋㅋㅋㅋㅋㅋㅋㅋㅋ",
	" 형": " 여자친구랑 대화한데이터로도",
	" 예뻐요": " ㅗㅗㅗㅗ",
	" ㅗㅗㅗㅗ": " 오버워치하자",
	" 오버워치하자": "//open.kakao.com/o/gPnlUxk",
	"//open.kakao.com/o/gPnlUxk": " ㅋㅋㅋㅋㅋㅋㅋㅋㅋㅋㅋㅋㅋㅋㅋㅋㅋㅋㅋㅋㅋㅋㅋㅋㅋㅋㅋ",
	" ㅋㅋㅋㅋㅋㅋㅋㅋㅋㅋㅋㅋㅋㅋㅋㅋㅋㅋㅋㅋㅋㅋㅋㅋㅋㅋㅋ": " 헹",
	" 헹": " 형",
	" 사진": " 키야",
	" 이거왜이래요.ㅋㅋㅋㅋㅋㅋㅋㅋㅋㅋㅋㅋㅋㅋㅋ": " ㅋㅋㅋㅋㅋ나도몰렄ㅋㅋ",
	" ㅋㅋㅋㅋㅋ나도몰렄ㅋㅋ": " 아웃오브컨트롤...",
	" 아웃오브컨트롤...": " ㅋㅋㅋㅋㅋㅋㅋㅋㅋ무슨 원리에요??",
	" ㅋㅋㅋㅋㅋㅋㅋㅋㅋ무슨 원리에요??": " 신기하네요 채팅봇 ㄷㄷ",
	" 신기하네요 채팅봇 ㄷㄷ": " 그냥 단어랑 어구 비슷한 멘트 찾아서 응답해주는건데",
	" 그냥 단어랑 어구 비슷한 멘트 찾아서 응답해주는건데": " 우리나라 말이 너무 복잡해서 힘듬ㅠㅠ",
	" 우리나라 말이 너무 복잡해서 힘듬ㅠㅠ": " 오호~ 저런거 예제가 있어요? 아니면 형이 직접 다 짜본거에요??",
	" 오호~ 저런거 예제가 있어요? 아니면 형이 직접 다 짜본거에요??": " 일단은 혼자 해본건데 혹시 참고할만한 좋은데 있으면 알려줘ㅠㅠㅋㅋ",
	" 일단은 혼자 해본건데 혹시 참고할만한 좋은데 있으면 알려줘ㅠㅠㅋㅋ": " 친구가 예전에",
	" 친구가 예전에": " 심심이에서",
	" 심심이에서": " 일했었는데",
	" 일했었는데": " 물어볼게요",
	" 물어볼게요": " 근데 형 지금 한참 시험기간아니에요???",
	" 근데 형 지금 한참 시험기간아니에요???": " 따로플젝할 시간 있어요?? ㄷㄷ",
	" 따로플젝할 시간 있어요?? ㄷㄷ": " 오오 고마워ㅎㅎ",
	" 오오 고마워ㅎㅎ": " 지난주에 끝나구",
	" 같이 로직을 짤 사람을 구하고있음ㅋㅋ": " 이제 셤 공부시작해야지...",
	" 이제 셤 공부시작해야지...": " ㅠㅠ",
	" ㅠㅠ": " 사진",
	" ㅋㅋㅋㅋㅋㅋ화이팅이에요 ㅠㅠ": " 고맙당ㅠㅠ",
	" 고맙당ㅠㅠ": " 형형",
	" 형형": " 저 물어볼게 있어요!!",
	" 웅웅": " 딥러닝",
	" 물어볼게 있는데요 ㅋㅋ": " 프로그래밍 언어론 들으셨었쬬?",
	" 프로그래밍 언어론 들으셨었쬬?": " 아니아직ㅋㅋ",
	" 아니아직ㅋㅋ": " 다음학기에 들을듯",
	" 다음학기에 들을듯": " 아아",
	" 아아": " 그런가요?",
	" 그럼 형": " 저번에 엄청 고생하던게",
	" 저번에 엄청 고생하던게": " 컴파일러였어요?",
	" 컴파일러였어요?": " 그 어셈블리였던거 같은디",
	" 그 어셈블리였던거 같은디": " 아하...",
	" 아하...": " ㅋㅋㅋㅋㅋㅋ",
	" ㅋㅋㅋㅋㅋㅋ": " 그럼 다 아는거 아닙니까ㅋㅋㅋ",
	" 그렇군요": " 저도 거기서 인턴하겠냐고 제의받았어요!!",
	" 어셈블리로 도어락이랑 시계만드는거..": " 다음학기에 들으려는데",
	" 다음학기에 들으려는데": " 정확히 어떤거 배우는지 모르겠어서",
	" 정확히 어떤거 배우는지 모르겠어서": " 프로그래밍 언어론",
	" 프로그래밍 언어론": " 물어보려햇어요 ㅋㅋㅋ",
	" 물어보려햇어요 ㅋㅋㅋ": " 같이 들으면되겠네ㅎㅎ",
	" 같이 들으면되겠네ㅎㅎ": " ㅋㅋㅋ 좋아요 ㅋㅋㅋㅋ",
	" ㅋㅋㅋ 좋아요 ㅋㅋㅋㅋ": " 이건 소프트웨어과랑 컴공이랑 따로 열리는게 아닌가보네요",
	" 이건 소프트웨어과랑 컴공이랑 따로 열리는게 아닌가보네요": " 웅 그런듯ㅎㅎ",
	" 웅 그런듯ㅎㅎ": " 1년 더다녀야댐ㅅㅂ",
	" 1년 더다녀야댐ㅅㅂ": " ㅋㅋㅋㅋㅋㅋ",
	" 헐 저랑 똑같으심 ㅋㅋㅋ": " 형은 졸업하고 계획어떻게 돼요?",
	" 형은 졸업하고 계획어떻게 돼요?": " 몰러ㅋㅋㅋ",
	" 몰러ㅋㅋㅋ": " 미래가 불투명함",
	" 미래가 불투명함": " ㅋㅋㅋㅋㅋㅋㅋㅋㅋㅋㅋㅋ",
	" ㅋㅋㅋㅋㅋㅋㅋㅋㅋㅋㅋㅋ": " 저 너무 바빴어요 방학에 ㅋㅋㅋ",
	" 형은 투명한게 여러개인거지": " 불투명한게 아니자나요 ",
	" 불투명한게 아니자나요 ": " 투명 유리가 겹쳐서 불투명함ㅋㅋㅋ",
	" 투명 유리가 겹쳐서 불투명함ㅋㅋㅋ": " 너는?",
	" 너는?": " ㅋㅋㅋㅋㅋㅋㅋㅋㅋㅋㅋㅋㅋㅋㅋㅋㅋㅋ",
	" ㅋㅋㅋㅋㅋㅋㅋㅋㅋㅋㅋㅋㅋㅋㅋㅋㅋㅋ": " 저는 대학원 가려구요",
	" 저는 대학원 가려구요": " 굿굿ㅎㅎ",
	" 굿굿ㅎㅎ": " 나도 대학원 생각중",
	" 나도 대학원 생각중": " 오",
	" 오": " 듣기로",
	" 어디로요??": " 아직 멀랑ㅋㅋㅋ연구실 인턴도 해보고 그래야할듯",
	" 아직 멀랑ㅋㅋㅋ연구실 인턴도 해보고 그래야할듯": " ㅋㅋㅋㅋ 그렇군요",
	" ㅋㅋㅋㅋ 그렇군요": " 흐어",
	" 흐어": " 언제부터",
	" 언제부터": " 연구실 컨택 해볼거에요?",
	" 연구실 컨택 해볼거에요?": " 뭐 해도 내년 여름방학때 할거니까",
	" 뭐 해도 내년 여름방학때 할거니까": " 좀 여유있게 할라구",
	" 좀 여유있게 할라구": " 아직 확실한것도 아님ㅋㅋ",
	" 아직 확실한것도 아님ㅋㅋ": " 그렇군요 ㅋㅋㅋ",
	" 그렇군요 ㅋㅋㅋ": " 같은 시기에 대학원 가겠네요 형 ㅋㅋㅋ",
	" 같은 시기에 대학원 가겠네요 형 ㅋㅋㅋ": " 웅ㅋㅋㅋ",
	" 웅ㅋㅋㅋ": " 이번에 멋사 5기 운영진 안해?",
	" 이번에 멋사 5기 운영진 안해?": " 네 해요 ㅋㅋㅋ",
	" 네 해요 ㅋㅋㅋ": " 근데 많이 바빠질것 같아서 걱정이긴하네요 ㅠㅠ",
	" 근데 많이 바빠질것 같아서 걱정이긴하네요 ㅠㅠ": " 그래도 다행이네ㅎㅎ",
	" 그래도 다행이네ㅎㅎ": " 많이 안하는줄알고 걱정하고있었음ㅠㅠ",
	" 많이 안하는줄알고 걱정하고있었음ㅠㅠ": " 운영진이 많진 않아요 ㅠㅠ",
	" 운영진이 많진 않아요 ㅠㅠ": " 지금 4명인데",
	" 지금 4명인데": " 조금 뽑아야할것 같아요 사람을 ㅋㅋㅋ",
	" 조금 뽑아야할것 같아요 사람을 ㅋㅋㅋ": " 그려 그래야겠다ㅋㅋ",
	" 그려 그래야겠다ㅋㅋ": " 사진",
	" 이..이런게 도는데요 형?!": " 음 봤어ㅋㅋㅋ",
	" 음 봤어ㅋㅋㅋ": " ㅋㅋㅋㅋ하..한두개가아닌데",
	" ㅋㅋㅋㅋ하..한두개가아닌데": " 당황스립게^어요형",
	" 당황스립게^어요형": " 해명 댓글 달긴 했음..ㅠㅠ",
	" 해명 댓글 달긴 했음..ㅠㅠ": " 알려줘서 고맙다 혁렬아",
	" 알려줘서 고맙다 혁렬아": " 개당황함ㅋㅋㅋㅋ",
	" 개당황함ㅋㅋㅋㅋ": " ㅋㅋㅋㅋㅋㅋㅋㅋㅋㅋㅋㅋㅋㅋㅋㅋㅋㅋㅋㅋㅋㅋㅋㅋ",
	" ㅋㅋㅋㅋㅋㅋㅋㅋㅋㅋㅋㅋㅋㅋㅋㅋㅋㅋㅋㅋㅋㅋㅋㅋ": " 그쵸 한두개가 아니더라구요",
	" 그쵸 한두개가 아니더라구요": " ㅎㅎ고마웡",
	" ㅎㅎ고마웡": " 새해복마니받으렴(하트뿅)",
	" 새해복마니받으렴(하트뿅)": " ㅋㅋㅋㅋㅋㅋ 형도 새해복 많이 받으세요~",
	" ㅋㅋㅋㅋㅋㅋ 형도 새해복 많이 받으세요~": " 병욱이형 ㅜㅜㅜ 미안해요 ㅜㅜ 정신이 없어서 제가 빨리 못올려드렸네요 ㅜㅜ",
	" 병욱이형 ㅜㅜㅜ 미안해요 ㅜㅜ 정신이 없어서 제가 빨리 못올려드렸네요 ㅜㅜ": " 아냐 갠차나ㅋㅋㅋ같이 멋사 홍보도 되고 좋을듯!",
	" 아냐 갠차나ㅋㅋㅋ같이 멋사 홍보도 되고 좋을듯!": " 화이팅ㅎㅎ",
	" 화이팅ㅎㅎ": " ㅋㅋㅋ 아니에요 정말 미안해요 ㅜㅜ",
	" ㅋㅋㅋ 아니에요 정말 미안해요 ㅜㅜ": " 형도 화이팅이에요!! ㅎㅎ",
	" 형도 화이팅이에요!! ㅎㅎ": " 혁렬아 이따 잠깐 놀러가도 되니ㅋㅋ",
	" 혁렬아 이따 잠깐 놀러가도 되니ㅋㅋ": " 네!! 오세요오세요",
	" 네!! 오세요오세요": " 7시에 화분이에요!!",
	" 7시에 화분이에요!!": " 엥 거기로 바로가는겨?ㅋㅋ",
	" 엥 거기로 바로가는겨?ㅋㅋ": " 네 바로 거기서 모인다네요 ㅋㅋ",
	" 네 바로 거기서 모인다네요 ㅋㅋ": " 7시 반쯤?",
	" 7시 반쯤?": " 오시는게 더 나을것 같아요",
	" 오시는게 더 나을것 같아요": " 다들 늦을듯해요 ㅋㅋㅋㅋ",
	" 다들 늦을듯해요 ㅋㅋㅋㅋ": " 병욱이형!",
	" 병욱이형!": " 보이스톡 해요",
	"34": " 010 9122 3952",
	" 010 9122 3952": " ㅋㅋ번호가 없었네",
	" ㅋㅋ번호가 없었네": " 01072752782",
	" 01072752782": " ㅋㅋㅋ 저장했습니당",
	" ㅋㅋㅋ 저장했습니당": " 굿굿",
	" 굿굿": " 뭐여ㅋㅋㅋ",
	" 뭐여ㅋㅋㅋ": " 콜드플레이 음악듣다가 끊겼자나",
	" 콜드플레이 음악듣다가 끊겼자나": " 책임져",
	" 책임져": " (이모티콘) ",
	" (이모티콘) ": " 형형!!",
	" ㅋㅋㅋ ㅋㅋㅋ": " 어 형 ㅋㅋㅋ",
	" 어 형 ㅋㅋㅋ": " 어제 제가 술 많이먹어서",
	" 어제 제가 술 많이먹어서": " 전화잘못했던것 같아요 ㅋㅋㅋ",
	" 전화잘못했던것 같아요 ㅋㅋㅋ": " 죄송해요 ㅜㅜ",
	" 죄송해요 ㅜㅜ": " 갠차너ㅋㅋㅋ",
	" 갠차너ㅋㅋㅋ": " 내가 항상 전화번호부 맨위에 있어서 이런경우 엄청많음ㅋㅋㅋ",
	" 내가 항상 전화번호부 맨위에 있어서 이런경우 엄청많음ㅋㅋㅋ": " ㅋㅋㅋㅋㅋㅋㅋㅋㅋㅋㅋㅋ",
	" 강씨들의 비애인가요 ㅋㅋㅋ": " ㅋㅋㅋㅋㅋ뭐 이렇게라도 연락을 해준다면야....",
	" ㅋㅋㅋㅋㅋ뭐 이렇게라도 연락을 해준다면야....": " ㅋㅋㅋㅋㅋㅋ",
	" 에이 형에겐": " 라이언봇이 있자나요",
	" 라이언봇이 있자나요": " 먼저 말걸기전까진 상대안해줌ㅠㅠㅋㅋㅋㅋ",
	" 먼저 말걸기전까진 상대안해줌ㅠㅠㅋㅋㅋㅋ": " 형",
	" GAN": " 이란거 알아요 혹시?",
	" 이란거 알아요 혹시?": "//github.com/ankitkv/TextGAN",
	"//github.com/ankitkv/TextGAN": " 요즘 뜨고 있던데 자세히는 공부 안해봄ㅋㅋ",
	" 요즘 뜨고 있던데 자세히는 공부 안해봄ㅋㅋ": " 이걸",
	" 이걸": " 이용하면",
	" 이용하면": " 먼저 말거는",
	" 먼저 말거는": " 챗봇을 만들수 있지않을까",
	" 챗봇을 만들수 있지않을까": " 생각했어요 ㅋㅋㅋ",
	" 생각했어요 ㅋㅋㅋ": " 오옹 한번 봐바야게따ㅋㅋ",
	" 오옹 한번 봐바야게따ㅋㅋ": " 페북에 자주 올라오길래 궁금해씀",
	" 페북에 자주 올라오길래 궁금해씀": " 형형",
	"//github.com/rlcode/reinforcement-learning": " 스타좀 부탁드려요 ^^ㅋㅋㅋㅋㅋㅋ",
	" 스타좀 부탁드려요 ^^ㅋㅋㅋㅋㅋㅋ": " 오키오킹ㅋㅋ",
	" 오키오킹ㅋㅋ": " 형 ㅋㅋㅋㅋ",
	" 형 ㅋㅋㅋㅋ": " 저거 깃허브",
	" 저거 깃허브": " 트렌딩 올라갔어요",
	" 트렌딩 올라갔어요": " github.com/trending/python",
	" github.com/trending/python": " 헐대박ㅋㅋ",
	" 헐대박ㅋㅋ": " 홧팅(굿)",
	" 홧팅(굿)": " 대학원 문 박살내고 들어가겠네ㅋㅋㅋ",
	" 대학원 문 박살내고 들어가겠네ㅋㅋㅋ": " ㅋㅋㅋㅋ",
	" ㅋㅋㅋㅋ": " 그러드라구요",
	" 저것도 대학원에서 좀": " 인정해주려나요",
	" 인정해주려나요": " 당연하지ㅋㅋ",
	" 당연하지ㅋㅋ": " 논문 쓴거보다 더 인정해줄듯",
	" 논문 쓴거보다 더 인정해줄듯": " ㅋㅋㅋㅋ",
	" 좀 아쉬운건": " 제가 따로 작업하던 레포가 잇었는데",
	" 제가 따로 작업하던 레포가 잇었는데": " 사진",
	" 이건 제 코드 다 옮기면서": " 제 커밋 이력이 다사라졌어요",
	" 제 커밋 이력이 다사라졌어요": " 에고ㅜㅜ",
	" 에고ㅜㅜ": " 앞으로 쌓으면 되니까 괜춘ㅋㅋ",
	" 앞으로 쌓으면 되니까 괜춘ㅋㅋ": " 으헝ㅇ어엉ㅇ어엉",
	" 으헝ㅇ어엉ㅇ어엉": " ㅋㅋㅋㅋㅋㅋ",
	" 흐아 그래도 반응이": " 생각보다 너무좋아서",
	" 생각보다 너무좋아서": " 행복하네요",
	" 행복하네요": " (굿)",
	" 혁렬아 혹시 강화학습이나 GAN 같이 공부할 수 있는 스터디그룹이나 모임같은거 있으면 추천해줄수 있니ㅋㅋ": " 어어",
	" 어어": " 모두의 연구소",
	" 모두의 연구소": " 여기요!!",
	" 여기요!!": " GAN 은 저 요즘 하고 있는데",
	" GAN 은 저 요즘 하고 있는데": " 같이 할수 잇음 재밋겟네요",
	" 같이 할수 잇음 재밋겟네요": " 강화학습 GAN  둘다 저 하고 잇는건데..!!!",
	" 강화학습 GAN  둘다 저 하고 잇는건데..!!!": " 오호",
	" 오호": " 나도 껴주삼ㅋㅋㅋㅋ",
	" 나도 껴주삼ㅋㅋㅋㅋ": " ㅋㅋㅋ 저는 요즘",
	" ㅋㅋㅋ 저는 요즘": " 스터디는 안하고",
	" 스터디는 안하고": " 그냥",
	" 그냥": " 연구실에 있어요",
	" 연구실에 있어요": "//www.modulabs.co.kr/",
	"//www.modulabs.co.kr/": " 여기 들어가시면",
	" 여기 들어가시면": " 저번에 가고싶다던 데에서 하고 있나보구나ㅎㅎ",
	" 저번에 가고싶다던 데에서 하고 있나보구나ㅎㅎ": " 웅웅",
	" 딥러닝": " 인텐시브 코스",
	" 인텐시브 코스": " 여기서",
	" 여기서": " 강화학습이랑 gan 꽤 하고 있는것 같아요 ㅋㅋ",
	" 강화학습이랑 gan 꽤 하고 있는것 같아요 ㅋㅋ": " 형은 인턴 계속 하고 계셔요?",
	" 형은 인턴 계속 하고 계셔요?": " 오오 고마워ㅎㅎ",
	" 지난주에 끝나구": " 결과 발표는 조만간 해주겠대ㅋㅋ",
	" 결과 발표는 조만간 해주겠대ㅋㅋ": " 우와",
	" 우와": " 결과 발표라는건",
	" 결과 발표라는건": " 인턴 중에서 일부만 채용되는거에요?",
	" 인턴 중에서 일부만 채용되는거에요?": " ㄷㄷㄷ",
	" ㄷㄷㄷ": " 웅….절반넘게 떨군다는 소문이....",
	" 웅….절반넘게 떨군다는 소문이....": " ㅠㅠ",
	" 여기 시간표 있던데": " 여기 전화번호 연락하면 되는건감?",
	" 여기 전화번호 연락하면 되는건감?": " 신청 절차가 따로 있엉?",
	" 신청 절차가 따로 있엉?": " 아마",
	" 아마": " 랩짱이라는 사람이 있는데",
	" 랩짱이라는 사람이 있는데": " 그분한테 연락하면 되는걸로 알고 있어요! ㅋㅋ",
	" 그분한테 연락하면 되는걸로 알고 있어요! ㅋㅋ": " 형 근데 자연어 처리쪽으로 가시는거 아니었어요?",
	" 형 근데 자연어 처리쪽으로 가시는거 아니었어요?": " 뭐 그렇긴 한데 딥러닝이라는게 명확한 경계가 있는게 아니니까ㅋㅋ",
	" 뭐 그렇긴 한데 딥러닝이라는게 명확한 경계가 있는게 아니니까ㅋㅋ": " 자연어처리를 강화학습이나 GAN이랑 연계해서 모델을 만들수도 있고",
	" 자연어처리를 강화학습이나 GAN이랑 연계해서 모델을 만들수도 있고": " 지식 도메인을 넓히는 차원에서ㅎㅎ",
	" 지식 도메인을 넓히는 차원에서ㅎㅎ": " 자연어 처리 연구 코스도 있던데 한번 알아봐야지ㅋㅋ",
	" 자연어 처리 연구 코스도 있던데 한번 알아봐야지ㅋㅋ": " 책 쓴거 지금 서점에서 팔고 있지?",
	" 책 쓴거 지금 서점에서 팔고 있지?": " ㅋㅋㅋㅋ 그렇군요 맞아요",
	" ㅋㅋㅋㅋ 그렇군요 맞아요": " 요즘 강화학습이 GAN에서도 쓰이고",
	" 요즘 강화학습이 GAN에서도 쓰이고": " 챗봇에서도 쓰이고",
	" 챗봇에서도 쓰이고": " ㅋㅋㅋㅋ",
	" 그러드라구요": " GAN으로 하는 클러스터링도 엄청 잘되고",
	" GAN으로 하는 클러스터링도 엄청 잘되고": " 네 팔고 있어요 !! ㅋㅋㅋ",
	" 네 팔고 있어요 !! ㅋㅋㅋ": " 사고나서 인증할게 책에 싸인해줘ㅋㅋ",
	" 사고나서 인증할게 책에 싸인해줘ㅋㅋ": " /ㅋㅋㅋㅋㅋㅋ 으악 ㅋㅋㅋ",
	" /ㅋㅋㅋㅋㅋㅋ 으악 ㅋㅋㅋ": " 해드릴께여 ㅋㅋㅋ",
	" 해드릴께여 ㅋㅋㅋ": " 싸인 만들어야겠네요 ㅋㅋㅋ",
	" 싸인 만들어야겠네요 ㅋㅋㅋ": " 스타되실 양반께서 아직도 싸인이 없다니…!!",
	" 스타되실 양반께서 아직도 싸인이 없다니…!!": " 모두의 연구소 DeepLAB 자연어처리반에 참여 희망 이메일 보냈음!!",
	" 모두의 연구소 DeepLAB 자연어처리반에 참여 희망 이메일 보냈음!!": " 고맙다 혁렬아ㅎㅎ",
	" 고맙다 혁렬아ㅎㅎ": " 크으",
	" 크으": " 라이언본 아버지께서",
	" 라이언본 아버지께서": " 저보고 스타라니요 ㅎㅎㅎ",
	" 저보고 스타라니요 ㅎㅎㅎ": " 화이팅이에요!! 요즘",
	" 화이팅이에요!! 요즘": " 모두연 엄청 커지고있으니",
	" 모두연 엄청 커지고있으니": " 가면 기회도 많을거에요!",
	" 가면 기회도 많을거에요!": " 그런거같더라구ㅎㅎ",
	" 그런거같더라구ㅎㅎ": " 화이팅합시다!!",
	" 화이팅합시다!!": " (이모티콘) ",
	" 네넵 !!": " 형형",
	" 저 물어볼게 있어요!!": " 엥 뭔데ㅋㅋ",
	" 엥 뭔데ㅋㅋ": " 저희 한양대멋사에서 다음학기에는 머신러닝관련된 프로젝트를 많이 하려고하는데요",
	" 아아 형": " 네이버에서 인턴하신곳이",
	" 네이버에서 인턴하신곳이": " 랩스에요? 클로바에요??",
	" 랩스에요? 클로바에요??": " 클로바ㅎㅎ",
	" 클로바ㅎㅎ": " 오오오",
	" 오오오": " 저도 같은 생각이에요",
	" 저도 거기서 인턴하겠냐고 제의받았어요!!": " 사진",
	" 결과 나왔다ㅎㅎ": " 먼저 가있을게ㅋㅋㅋ",
	" 먼저 가있을게ㅋㅋㅋ": " 웨와악",
	" 웨와악": " 먼저 가 계세요 형 ㅋㅋㅋㅋㅋㅋㅋㅋㅋ",
	" 먼저 가 계세요 형 ㅋㅋㅋㅋㅋㅋㅋㅋㅋ": " 웅웅 언넝와ㅋㅋ",
	" 웅웅 언넝와ㅋㅋ": " 내년 여름에 갈것 같네요 ㅋㅋㅋ",
	" 내년 여름에 갈것 같네요 ㅋㅋㅋ": " 크으 형 군대다녀온게",
	" 크으 형 군대다녀온게": " 세상에서 제일부럽다",
	" 세상에서 제일부럽다": " 네이버도 병특 있던데",
	" 네이버도 병특 있던데": " 한번 알아봐바ㅎㅎ",
	" 한번 알아봐바ㅎㅎ": " 거기서 병특하면 세상 꿀일듯",
	" 거기서 병특하면 세상 꿀일듯": " ㅋㅋㅋㅋㅋㅋ",
	" 네 여기서 인턴하는것도": " 병특을 위한",
	" 병특을 위한": " 밑걸음 이랄까효 ㅋㅋㅋ",
	" 밑걸음 이랄까효 ㅋㅋㅋ": " ㅋㅋ큰그림 지려따",
	" ㅋㅋ큰그림 지려따": " 홧팅ㅎㅎ",
	" 홧팅ㅎㅎ": " 와 근데 형 진짜 축하해요 ㅠㅠㅠ",
	" 와 근데 형 진짜 축하해요 ㅠㅠㅠ": " 입사 한달차 후기 기댜할게요 ㅋㅋㅋㅋㅋㅋ",
	" 입사 한달차 후기 기댜할게요 ㅋㅋㅋㅋㅋㅋ": " 응응 적나라한 후기를 전해줄게ㅋㅋㅋ",
	" 응응 적나라한 후기를 전해줄게ㅋㅋㅋ": " 네넵",
	" 네넵": " 아이디어 팩토리구요!",
	" 형 다음학기는 그냥 다니는거죠?!": " 응ㅋㅋ",
	" 응ㅋㅋ": " 네과목정도 들어ㅎㅎ",
	" 네과목정도 들어ㅎㅎ": " 와 ㅋㅋㅋ 많이들으시네요 ㅋㅋㅋ",
	" 와 ㅋㅋㅋ 많이들으시네요 ㅋㅋㅋ": " 혹시 F뜰까봐...ㅋㅋㅋ",
	" 혹시 F뜰까봐...ㅋㅋㅋ": " 2학기에도 연구실 가는거야?",
	" 2학기에도 연구실 가는거야?": " ㅋㅋㅋㅋㅋㅋㅋㅋㅋ F뜰가봐ㅋㅋㅋㅋㅋㅋㅋㅋㅋ",
	" ㅋㅋㅋㅋㅋㅋㅋㅋㅋ F뜰가봐ㅋㅋㅋㅋㅋㅋㅋㅋㅋ": " 네 계속 나가고있어요",
	" 네 계속 나가고있어요": " 전부나가진 않고",
	" 전부나가진 않고": " 랩미팅이나",
	" 랩미팅이나": " 플젝 미팅있을때 나가요",
	" 플젝 미팅있을때 나가요": " 글쿠나ㅎㅎ",
	" 글쿠나ㅎㅎ": " 다음주부터 모두연 나가려구",
	" 다음주부터 모두연 나가려구": " 오",
	" 듣기로": " 모두연 자연어처리",
	" 모두연 자연어처리": " 랩짱이",
	" 랩짱이": " 네이버에있는분이던데요?",
	" 네이버에있는분이던데요?": " 올ㅋ",
	" 올ㅋ": " 프로젝트에 참여하고있어요 ㅋㅋㅋ",
	" 그건 몰랐네ㅋㅋㅋ": " 좋다",
	" 좋다": " ㅎㅎ",
	" ㅎㅎ": " ㅋㅋㅋㅋㅋㅋ",
	" 저도 네이버갔다가": " 만나서 들었어요 ㅋㅋㅋ",
	" 만나서 들었어요 ㅋㅋㅋ": " ㅋㅋㅋ모르는척하다가",
	" ㅋㅋㅋ모르는척하다가": " 자연스럽게 얘기꺼내야지ㅎㅎ",
	" 자연스럽게 얘기꺼내야지ㅎㅎ": " 반응이 궁금하다ㅋㅋㅋ",
	" 반응이 궁금하다ㅋㅋㅋ": " ㅋㅋㅋㅋㅋㅋㅋㅋ",
	" ㅋㅋㅋㅋㅋㅋㅋㅋ": " 근데 해커톤은 다들 많이가서",
	" 👍👍👍크으": " 형 기분 좋으시겠어요",
	" 형 기분 좋으시겠어요": " 이렇게 네이버 타고",
	" 이렇게 네이버 타고": " 구글로 나갑시다형",
	" 구글로 나갑시다형": " ㅎㅎ좋지",
	" ㅎㅎ좋지": " 나도 커리어 쌓다가",
	" 나도 커리어 쌓다가": " 야간대학원으로라도 다니려구ㅋㅋ",
	" 야간대학원으로라도 다니려구ㅋㅋ": " 석사 이상은 필요할듯",
	" 석사 이상은 필요할듯": " 아아",
	" 그런가요?": " 지금 석사하는게 잘하는거네요 그럼 ㅋㅋㅋ",
	" 지금 석사하는게 잘하는거네요 그럼 ㅋㅋㅋ": " 아직은 잘 모르겠는데",
	" 아직은 잘 모르겠는데": " 하다보면 뭔가 한계를 느낄거같아서ㅜㅜ",
	" 하다보면 뭔가 한계를 느낄거같아서ㅜㅜ": " 네이버에서 돈모아서",
	" 네이버에서 돈모아서": " 미국으로 석사가요",
	" 미국으로 석사가요": " ㅋㅋㅋ",
	" ㅋㅋㅋ": " 석사하다가 병특으로 네이버가는게 슈퍼테그지ㅋㅋ",
	" 석사하다가 병특으로 네이버가는게 슈퍼테그지ㅋㅋ": " 크으....그게 진짜",
	" 크으....그게 진짜": " 슈퍼테크긴 하네요",
	" 슈퍼테크긴 하네요": " 네이버 병특 꼭 되길...휴",
	" 네이버 병특 꼭 되길...휴": " 한번 제의 들어온 게 있으니까 충분히 가능성 있어",
	" 한번 제의 들어온 게 있으니까 충분히 가능성 있어": " 잘해방ㅋㅋ",
	" 잘해방ㅋㅋ": " 네 형 꼭 네이버에서 봐요 ㅋㅋㅋㅋㅋㅋ",
	" 네 형 꼭 네이버에서 봐요 ㅋㅋㅋㅋㅋㅋ": " 와 그래도 형은",
	" 와 그래도 형은": " 들어가면",
	" 들어가면": " 지피유 맘껏 쓰시겠네 ㅠㅠ",
	" 지피유 맘껏 쓰시겠네 ㅠㅠ": " 음 그렇겠지?ㅋㅋㅋ",
	" 음 그렇겠지?ㅋㅋㅋ": " 연구실에도 시설 잘되어있자너ㅎㅎ",
	" 연구실에도 시설 잘되어있자너ㅎㅎ": " 저희는 지금 갑자기 사람이 많아져서",
	" 저희는 지금 갑자기 사람이 많아져서": " 지피유 좀 모자라요",
	" 지피유 좀 모자라요": " 곧 산다고는 하는데 ㅠ",
	" 곧 산다고는 하는데 ㅠ": " 형들껄 제가 뺏어쓸수는 없는노릇이라 ㅋㅋㅋ 아직 인턴이ㅠㅠ",
	" 형들껄 제가 뺏어쓸수는 없는노릇이라 ㅋㅋㅋ 아직 인턴이ㅠㅠ": " 네이버한테 안그래도",
	" 네이버한테 안그래도": " 지피유가 넘 불쌍하다ㅠㅠㅋㅋ",
	" 지피유가 넘 불쌍하다ㅠㅠㅋㅋ": " 서버지원 해달라고",
	" 서버지원 해달라고": " 하려구요 ㅋㅋㅋㅋㅋㅋ",
	" 하려구요 ㅋㅋㅋㅋㅋㅋ": " 클라우드 잘되어있는거 같더라ㅎㅎ",
	" 클라우드 잘되어있는거 같더라ㅎㅎ": " 학교에서 만나면 책에 싸인해줘유",
	" 학교에서 만나면 책에 싸인해줘유": " 가지고 갈게ㅋㅋ",
	" 가지고 갈게ㅋㅋ": " ㅋㅋㅋㅋㅋㅋㅋㅋㅋ",
	" ㅋㅋㅋㅋㅋㅋㅋㅋㅋ": " 음 뭐 되지 않을까?ㅋㅋ",
	" 부끄럽지만... 해드릴게요 ㅋㅋㅋ": " 응ㅋㅋ싸인 연습해두고",
	" 응ㅋㅋ싸인 연습해두고": " 학교에서 봅시당ㅎㅎ",
	" 학교에서 봅시당ㅎㅎ": " (이모티콘) 네형 !!!",
	" (이모티콘) 네형 !!!": " 사진",
	" 키야": " 모르는거 모아서 나중에 물어봐도 되지?ㅎㅎ",
	" 모르는거 모아서 나중에 물어봐도 되지?ㅎㅎ": " 크으아사셧군요!!",
	" 크으아사셧군요!!": " 당연하지요 ㅠㅠㅠ",
	" 당연하지요 ㅠㅠㅠ": " ㅎㅎ꼭 싸인받고말거야",
	" ㅎㅎ꼭 싸인받고말거야": " (굿)",
	" ㅋㅋㅋㅋㅋㅋ근데 저도 강화학습 잘몰라여.....ㅎㅎㅎ": " 제가 쓴부분은",
	" 제가 쓴부분은": " reinforce알고리즘까지",
	" reinforce알고리즘까지": " 코드랑 코드설명 썼어요!",
	" 코드랑 코드설명 썼어요!": " ㅋㅋㅋㅋㅋㅋ",
	" 그럼 다 아는거 아닙니까ㅋㅋㅋ": " 겸손한척 하기는ㅎㅎ",
	" 겸손한척 하기는ㅎㅎ": " 요즘 연구하고 있는 주제가 뭐야?",
	" 요즘 연구하고 있는 주제가 뭐야?": " 요즘은 GAN 하고있어요",
	" 요즘은 GAN 하고있어요": " 음 GAN으로다가",
	" 음 GAN으로다가": " 오우",
	" 오우": " 개애엔",
	" 개애엔": " 목소리 넣으면 얼굴을 그려주는",
	" 목소리 넣으면 얼굴을 그려주는": " 오디오 몽타쥬라는",
	" 오디오 몽타쥬라는": " 올ㅋ",
	" 프로젝트에 참여하고있어요 ㅋㅋㅋ": " 그리구",
	" 그리구": " 개인적으로 관심있는건",
	" 개인적으로 관심있는건": " 와 신기하다ㅋㅋㅋㅋ",
	" 묘사하는대로 그려주는건가": " 아뇨 말그대로",
	" 아뇨 말그대로": " 목소리의 특성으로",
	" 목소리의 특성으로": " 사람얼굴을...ㅇㅅㅇ",
	" 사람얼굴을...ㅇㅅㅇ": " 헐ㅋㅋㅋㅋㅋ",
	" 헐ㅋㅋㅋㅋㅋ": " 거의 미래기술 급 ㅋㅋㅋㅋㅋㅋㅋㅋㅋㅋㅋㅋㅋㅋㅋ",
	" 거의 미래기술 급 ㅋㅋㅋㅋㅋㅋㅋㅋㅋㅋㅋㅋㅋㅋㅋ": " 남성적인 목소리면",
	" 남성적인 목소리면": " 남자가 그려지고 그러는건가",
	" 남자가 그려지고 그러는건가": " 네 맞아요",
	" 네 맞아요": " 그것 까진 됐어요 ㅋㅋㅋㅋㅋㅋ",
	" 그것 까진 됐어요 ㅋㅋㅋㅋㅋㅋ": " 개인적으로 관심있는건",
	" 와 신기하다ㅋㅋㅋㅋ": " 챗봇이나",
	" 챗봇이나": " 자동 작곡할때",
	" 자동 작곡할때": " LSTM RNN 구조 많이쓰는데",
	" LSTM RNN 구조 많이쓰는데": " Structure에 대한걸 잘못배우는 경향이있어서",
	" Structure에 대한걸 잘못배우는 경향이있어서": " 거기에 RL을 요즘 많이 붙이더라구요",
	" 거기에 RL을 요즘 많이 붙이더라구요": " 그쪽 논문들좀 보는거랑",
	" 그쪽 논문들좀 보는거랑": " 음.. 그리고 강화학습쪽에선 Continous control 쪽 베이스라인 논문들 봐보고있어요!",
	" 음.. 그리고 강화학습쪽에선 Continous control 쪽 베이스라인 논문들 봐보고있어요!": " 오오…뭔가 대단해보인다…",
	" 오오…뭔가 대단해보인다…": " 열심히 연구해서 네이버에 병특으로 꼭 오렴ㅎㅎ",
	" 열심히 연구해서 네이버에 병특으로 꼭 오렴ㅎㅎ": " 네 ㅠㅠㅠ 꼭 가고프네요",
	" 네 ㅠㅠㅠ 꼭 가고프네요": " 닙스에 논문하나 내면 문 뿌실텐데 ㅠㅠㅠㅠ  ㅋㅋㅋ",
	" 닙스에 논문하나 내면 문 뿌실텐데 ㅠㅠㅠㅠ  ㅋㅋㅋ": " ㅎㅎ충분히 할수 있엉",
	" ㅎㅎ충분히 할수 있엉": " 내면 되지!",
	" 내면 되지!": " 허헛",
	" 허헛": " ㅋㅋㅋㅋㅋㅋㅋㅋㅋ넵",
	" ㅋㅋㅋㅋㅋㅋㅋㅋㅋ넵": " 꿈은 크게 가지랬어요",
	" 꿈은 크게 가지랬어요": " 일단 인턴제의 왔다는것만으로도 충분하지!",
	" 일단 인턴제의 왔다는것만으로도 충분하지!": " 이번에 skt brain 에서",
	" 이번에 skt brain 에서": " 97년생짜리",
	" 97년생짜리": " 여자인턴이",
	" 여자인턴이": " nips에 논문냈어요 ㅋㅋㅋㅋㅋㅋ",
	" nips에 논문냈어요 ㅋㅋㅋㅋㅋㅋ": " 캬",
	" 캬": " 나도 좀더 일찍 시작했더라면ㅠㅠ",
	" 나도 좀더 일찍 시작했더라면ㅠㅠ": " 너가 많이 부럽구나 혁렬아ㅠㅠ",
	" 너가 많이 부럽구나 혁렬아ㅠㅠ": " 열심히 연구해서 나중에 나좀 캐리해주렴..ㅠㅠ",
	" 열심히 연구해서 나중에 나좀 캐리해주렴..ㅠㅠ": " ㅠㅠㅠㅠ 아니에요 형",
	" ㅠㅠㅠㅠ 아니에요 형": " 여기는 다들 뉴비라서 형은 저보다 훨씬빨리 배우실거에요 ㅠㅠㅠ특히나 네이버란 환경에서 연구하시면",
	" 여기는 다들 뉴비라서 형은 저보다 훨씬빨리 배우실거에요 ㅠㅠㅠ특히나 네이버란 환경에서 연구하시면": " 크...",
	" 크...": " 은혜롭네요 ㅠ 저좀 네이버로 이끌이줘여 ㅠㅠ",
	" 은혜롭네요 ㅠ 저좀 네이버로 이끌이줘여 ㅠㅠ": " 서로 도움 주고받는거지 뭐ㅎㅎ 그래도 내 주변 친구들 중에는 너가 제일 자기 좋아하는분야 찾아서 잘 하고 있으니까 걱정안해도 되ㅎㅎ",
	" 서로 도움 주고받는거지 뭐ㅎㅎ 그래도 내 주변 친구들 중에는 너가 제일 자기 좋아하는분야 찾아서 잘 하고 있으니까 걱정안해도 되ㅎㅎ": " 크으.. 사실 형도 제 주변에서 그런데 ㅋㅋㅋㅋㅋㅋㅋㅋㅋ",
	" 크으.. 사실 형도 제 주변에서 그런데 ㅋㅋㅋㅋㅋㅋㅋㅋㅋ": " 라이언봇 큰그림 ㅇㅅㅇ..!!!!!",
	" 라이언봇 큰그림 ㅇㅅㅇ..!!!!!": " 넵 우리 열심히해서 좋은곳에서 만나요 ㅠㅠㅠ 네이버든어디든 ㅠㅠ",
	" 넵 우리 열심히해서 좋은곳에서 만나요 ㅠㅠㅠ 네이버든어디든 ㅠㅠ": " 그래그래 화이팅!!",
	" 그래그래 화이팅!!": " (이모티콘) ",
	" 형형!!": " 물어볼게있어요?",
	" 물어볼게있어요?": " !",
	" !": " 엥 뭔데ㅋㅋ",
	" 저희 한양대멋사에서 다음학기에는 머신러닝관련된 프로젝트를 많이 하려고하는데요": " 혹시 형이 챗봇에 대해 간단히 강의해주실수있을까하구요 ㅋㅋㅋㅋㅋㅋ",
	" 혹시 형이 챗봇에 대해 간단히 강의해주실수있을까하구요 ㅋㅋㅋㅋㅋㅋ": " 혹시 시간이 안나시면 어떤 자료를 보고 강의준비해야 좋을지 알려주시면ㅠㅠ 감사하겠습니다 형 ㅋㅋㅋㅋㅋㅋ",
	" 혹시 시간이 안나시면 어떤 자료를 보고 강의준비해야 좋을지 알려주시면ㅠㅠ 감사하겠습니다 형 ㅋㅋㅋㅋㅋㅋ": " 당연히 가능하지!",
	" 당연히 가능하지!": " 언제쯤?",
	" 언제쯤?": " 오오",
	" 오오": " 시간은 아직 정해야해요!!",
	" 시간은 아직 정해야해요!!": " 우아아아앍",
	" 우아아아앍": " 챗봇왕의 강의들을수 있는검니까!",
	" 챗봇왕의 강의들을수 있는검니까!": " 별거 없는데....ㅋㅋㅋ",
	" 별거 없는데....ㅋㅋㅋ": " 정해지면 일주일 전에 알려줘~~",
	" 정해지면 일주일 전에 알려줘~~": " 넵!!!!",
	" 넵!!!!": " 고마워요 형 ㅠㅠ",
	" 고마워요 형 ㅠㅠ": " 당연히 해줘야지ㅎㅎ멋사에 해준게 없어성ㅜㅜ",
	" 당연히 해줘야지ㅎㅎ멋사에 해준게 없어성ㅜㅜ": " 그것말고도 다른 도움 필요하면 언제든지 얘기해~~",
	" 그것말고도 다른 도움 필요하면 언제든지 얘기해~~": " 네 형 !!! ㅋㅋㅋ",
	" 네 형 !!! ㅋㅋㅋ": " 아 형",
	" 아 형": " 그 저희 멋사 모임은",
	" 그 저희 멋사 모임은": " 이제 다음주 수요일부터 시작인데요",
	" 이제 다음주 수요일부터 시작인데요": " 매주 수요일인데",
	" 매주 수요일인데": " 혹시 형 좀 한가로워질때가 언제세요?",
	" 혹시 형 좀 한가로워질때가 언제세요?": " 어 음",
	" 어 음": " 항상 한가해...",
	" 항상 한가해...": " ㅋㅋㅋㅋㅋ",
	" ㅋㅋㅋㅋㅋㅋㅋㅋㅋㅋㅋ": " 크으... 취업 뽀갠 자의",
	" 크으... 취업 뽀갠 자의": " 위엄인가요",
	" 위엄인가요": " 후우후우",
	" 후우후우": " 그동안 너무 정신없이 살아온거 같아서",
	" 그동안 너무 정신없이 살아온거 같아서": " 슬로라이프로 살고있어ㅋㅋ",
	" 슬로라이프로 살고있어ㅋㅋ": " 오오오",
	" 저도 같은 생각이에요": " 당장 그럴순 없지만",
	" 당장 그럴순 없지만": " 대학원 입시랑 이것저것 해야할거 끝내고나면",
	" 대학원 입시랑 이것저것 해야할거 끝내고나면": " 저도 진자",
	" 저도 진자": " 맘먹고 한가해지려구요",
	" 맘먹고 한가해지려구요": " 뭔가 막 뭐없어도",
	" 뭔가 막 뭐없어도": " 불안하고 막 이래서",
	" 불안하고 막 이래서": " 항상 정신없었으니까 ㅋㅋㅋ",
	" 항상 정신없었으니까 ㅋㅋㅋ": " 마자마자 그렇게 살다보면 가끔 현자타임이 올때가 있음....",
	" 마자마자 그렇게 살다보면 가끔 현자타임이 올때가 있음....": " 멋사 잘 되고 있어?",
	" 멋사 잘 되고 있어?": " 멋사는 음 저는 잘 참여를 안해서 모르겠어요",
	" 멋사는 음 저는 잘 참여를 안해서 모르겠어요": " ㅋㅋㅋㅋㅋㅋㅋㅋ",
	" 근데 해커톤은 다들 많이가서": " 열심히 한것 같던데요?",
	" 열심히 한것 같던데요?": " 그럼 성공한거 아닌가요!? ㅋㅋㅋ",
	" 그럼 성공한거 아닌가요!? ㅋㅋㅋ": " 머야 왜케 관심이 없어ㅋㅋㅋㅋㅋ",
	" 머야 왜케 관심이 없어ㅋㅋㅋㅋㅋ": " 운영진 아니십니까!",
	" 운영진 아니십니까!": " ㅋㅋㅋㅋㅋㅋㅋㅋㅋㅋㅋㅋ",
	" 저 너무 바빴어요 방학에 ㅋㅋㅋ": " 학기중에는 강의도하고했는데 ㅋㅋㅋ",
	" 학기중에는 강의도하고했는데 ㅋㅋㅋ": " 지금도 많이 바쁘지 않냐ㅋㅋㅋㅋ",
	" 지금도 많이 바쁘지 않냐ㅋㅋㅋㅋ": " 해커톤에서 우리학교에서 상탄거 있엉?",
	" 해커톤에서 우리학교에서 상탄거 있엉?": " ㅋㅋㅋ 네 많이바빠요 ㅠㅠ",
	" ㅋㅋㅋ 네 많이바빠요 ㅠㅠ": " 어 그건 모르겠네요?! ㅋㅋㅋㅋㅋㅋㅋㅋㅋㅋㅋㅋㅋㅋㅋ",
	" 어 그건 모르겠네요?! ㅋㅋㅋㅋㅋㅋㅋㅋㅋㅋㅋㅋㅋㅋㅋ": " 물어봐야겠다...",
	" 물어봐야겠다...": " 완전 관심이 없넹ㅋㅋㅋㅋㅋ",
	" 완전 관심이 없넹ㅋㅋㅋㅋㅋ": " 강의 일정 잡히면 알려줘~~",
	" 강의 일정 잡히면 알려줘~~": " 이제 다시 가지려구요...ㅎㅎ",
	" 이제 다시 가지려구요...ㅎㅎ": " 형 혹시 다음주 수요일은 되시나요??",
	" 형 혹시 다음주 수요일은 되시나요??": " 일주일 전은 아니지만 ㅠㅠ",
	" 일주일 전은 아니지만 ㅠㅠ": " 헛 그때는 다른 일정이 있어서ㅠㅠ",
	" 헛 그때는 다른 일정이 있어서ㅠㅠ": " 그 다음주는 가능할듯!",
	" 그 다음주는 가능할듯!": " 형 그럼 다음주 수요일로 확정해도 될까요??",
	" 형 그럼 다음주 수요일로 확정해도 될까요??": " 응ㅎㅎ몇시야?",
	" 응ㅎㅎ몇시야?": " 7시에요 !! ㅋㅋ",
	" 7시에요 !! ㅋㅋ": " 아 그리구 형 혹시 제 친구중에",
	" 아 그리구 형 혹시 제 친구중에": " 인테리어 관련된 스타트업을 하는 친구가 있는데",
	" 인테리어 관련된 스타트업을 하는 친구가 있는데": " 자기네 회사에 상담 시스템을",
	" 자기네 회사에 상담 시스템을": " 챗봇으로 전환하고 싶다고",
	" 챗봇으로 전환하고 싶다고": " 주변에 챗봇 하시는 분 있으면 소개좀 시켜달라고 하는데요",
	" 주변에 챗봇 하시는 분 있으면 소개좀 시켜달라고 하는데요": " 혹시 형 번호 알려줘봐도 될까요?",
	" 혹시 형 번호 알려줘봐도 될까요?": " 아 그렇구나ㅎㅎ",
	" 아 그렇구나ㅎㅎ": " 응응 괜찮아~~",
	" 응응 괜찮아~~": " 네엡 !! 고마워요 형 ㅠㅠ",
	" 네엡 !! 고마워요 형 ㅠㅠ": " 요즘 계속",
	" 요즘 계속": " 부탁만 드리는것 같네요 ㅠㅠ",
	" 부탁만 드리는것 같네요 ㅠㅠ": " 아니야ㅎㅎ",
	" 아니야ㅎㅎ": " 나중에 다 받아먹을거니까 괜찮아ㅎㅎ",
	" 나중에 다 받아먹을거니까 괜찮아ㅎㅎ": " ㅋㅋㅋㅋㅋㅋㅋㅋㅋㅋㅋㅋㅋㅋㅋㅋㅋㅋㅋ",
	" ㅋㅋㅋㅋㅋㅋㅋㅋㅋㅋㅋㅋㅋㅋㅋㅋㅋㅋㅋ": " 그래욥 ㅋㅋㅋㅋㅋㅋㅋ",
	" 그래욥 ㅋㅋㅋㅋㅋㅋㅋ": " 뽑아가실게 있으면 좋겠네요 ㅠㅠㅠㅠ 얼른 얼른 돈벌어야겠어요 ㅋㅋㅋ",
	" 뽑아가실게 있으면 좋겠네요 ㅠㅠㅠㅠ 얼른 얼른 돈벌어야겠어요 ㅋㅋㅋ": " 그래그래ㅎㅎ",
	" 그래그래ㅎㅎ": " 형",
	" (신나)": " 그분한테 아직 연락이 없네ㅠㅠ",
	" 그분한테 아직 연락이 없네ㅠㅠ": " 생판 모르는사람한테 이런 대접받으니까 되게 기분 나쁘다(흑흑)",
	" 생판 모르는사람한테 이런 대접받으니까 되게 기분 나쁘다(흑흑)": " 나중에 만나게되면 잘 전달해주렴ㅠㅠ",
	" 나중에 만나게되면 잘 전달해주렴ㅠㅠ": " 어제 얘기했었는데 늦은시간에 카톡보다는 정식으로 사과드리겠다고 그랬었어요 ㅠㅠ",
	" 어제 얘기했었는데 늦은시간에 카톡보다는 정식으로 사과드리겠다고 그랬었어요 ㅠㅠ": " 앗 그랬구나ㅜㅜ",
	" 앗 그랬구나ㅜㅜ": " 정식으로 사과한다는게 어떤의미인지는 모르겠지만",
	" 정식으로 사과한다는게 어떤의미인지는 모르겠지만": " 네네네 ㅜㅜㅜ 곧 연락 갈거에요 형 ㅠㅠ 정말 기분 나쁘실만해요",
	" 네네네 ㅜㅜㅜ 곧 연락 갈거에요 형 ㅠㅠ 정말 기분 나쁘실만해요": " 저도 엄청 뭐라했어요",
	" 저도 엄청 뭐라했어요": " 직접 볼생각은 없다고 전해줘ㅜㅜ",
	" 직접 볼생각은 없다고 전해줘ㅜㅜ": " 다신이런거 부탁하지말라고",
	" 다신이런거 부탁하지말라고": " 네넵",
	" ㅠㅠㅠ": " (흑흑)",
	" (흑흑)": " 도움되라고 형 소개시켜드린건데",
	" 도움되라고 형 소개시켜드린건데": " 형 기분 상하게만하고 ㅠㅠ",
	" 형 기분 상하게만하고 ㅠㅠ": " 진짜 ㅠㅠ 제가 면목이없네요 형...",
	" 진짜 ㅠㅠ 제가 면목이없네요 형...": " 이상한 사람이 생각보다 많다는건 이미 알고 있어서 괜찮아ㅋㅋ",
	" 이상한 사람이 생각보다 많다는건 이미 알고 있어서 괜찮아ㅋㅋ": " 다만 나같은 피해자가 더 나오지 않았으면 하는 바람에서...",
	" 다만 나같은 피해자가 더 나오지 않았으면 하는 바람에서...": " 암튼 이래저래 신경쓰게 해서 입장이 곤란하겠네(흑흑)",
	" 암튼 이래저래 신경쓰게 해서 입장이 곤란하겠네(흑흑)": " 잘 부탁해요ㅜㅜ",
	" 잘 부탁해요ㅜㅜ": " 아니에요 ㅠㅠ 형이 신경쓰이게하신게 아니죠 ㅠㅠ",
	" 아니에요 ㅠㅠ 형이 신경쓰이게하신게 아니죠 ㅠㅠ": " 그사람 잘못이죠 다 ㅜㅜ",
	" 그사람 잘못이죠 다 ㅜㅜ": " 제가 다시한번 잘 전할게요",
	" 제가 다시한번 잘 전할게요": " 응응ㅜㅜ",
	" 응응ㅜㅜ": " 멋사친구들 C9 계정 다 있지?ㅋㅋ",
	" 멋사친구들 C9 계정 다 있지?ㅋㅋ": " 1. C9 계정",
	" 1. C9 계정": "//center-pf.kakao.com/ 에서 플러스친구 하나씩 만들기",
	"//center-pf.kakao.com/ 에서 플러스친구 하나씩 만들기": " 멋사친구들에게 전달부탁해ㅎㅎ",
	" 멋사친구들에게 전달부탁해ㅎㅎ": " 네넵 알겟습니다!!",
	" 네넵 알겟습니다!!": " 형",
	" 공지 다 햇습니다": " 아직 연락 안왔죠?",
	" 아직 연락 안왔죠?": " 이놈 진짜 못쓰겠네요 ㅠㅠ",
	" 이놈 진짜 못쓰겠네요 ㅠㅠ": " 제 카톡도 씹어버려서는... ;;;;;;",
	" 제 카톡도 씹어버려서는... ;;;;;;": " 세상에 이상한사람 많다니깐ㅋㅋ",
	" 세상에 이상한사람 많다니깐ㅋㅋ": " 그냥 없던일로 하고 싹 잊어버립시다",
	" 그냥 없던일로 하고 싹 잊어버립시다": " 저야 이런 면모를 알게됐다고는 하지만 ㅠㅠ",
	" 저야 이런 면모를 알게됐다고는 하지만 ㅠㅠ": " 형께서도 같이 ㅠㅠ",
	" 형께서도 같이 ㅠㅠ": " 그러셔서 너무죄송하네요",
	" 그러셔서 너무죄송하네요": " 아니야 괜차나ㅎㅎ",
	" 아니야 괜차나ㅎㅎ": " 이런적 꽤 많아서 익숙함ㅋㅋㅋ",
	" 이런적 꽤 많아서 익숙함ㅋㅋㅋ": " 아 그리구",
	" 아 그리구": " 네넵",
	" 각자 만들고 싶은거 생각도 해왔으면 좋겠어!": " 그것두 전달해줘ㅋㅋ",
	" 그것두 전달해줘ㅋㅋ": " 아아 그렇군요!! 알겠습니다 ㅎㅎㅎㅎ",
	" 아아 그렇군요!! 알겠습니다 ㅎㅎㅎㅎ": " 감사해요 형 ㅠㅠ",
	" 감사해요 형 ㅠㅠ": " 내일뵈어요!!",
	" 내일뵈어요!!": " 그래그랭ㅎㅎ",
	" 그래그랭ㅎㅎ": " 거기 아이디어 팩토리에서 하는거지?",
	" 거기 아이디어 팩토리에서 하는거지?": " 7시였나ㅋㅋ",
	" 7시였나ㅋㅋ": " 네넵",
	" 아이디어 팩토리구요!": " 한 7시 20분정도까지?",
	" 한 7시 20분정도까지?": " 좀 천천히 오시는게 좋을 것 같아요 ! ㅋㅋ",
	" 좀 천천히 오시는게 좋을 것 같아요 ! ㅋㅋ": " 사람들이 딱 7시에 모이지도 않구",
	" 사람들이 딱 7시에 모이지도 않구": " 창대형도 좀 늦는다구해서",
	" 창대형도 좀 늦는다구해서": " 그래그래ㅎㅎ",
	" 여자친구랑 대화한데이터로도": " 챗봇 만들수있을까요",
	" 챗봇 만들수있을까요": " ㅋㅋㅋㅋㅋㅋㅋㅋㅋ",
	" 음 뭐 되지 않을까?ㅋㅋ": " 저는 주제 그걸로 선정해서..ㅎㅎ",
	" 저는 주제 그걸로 선정해서..ㅎㅎ": " 여자친구챗봇!ㅋㅋㅋㅋㅋㅋ",
	" 여자친구챗봇!ㅋㅋㅋㅋㅋㅋ": " 좋은 아이디어네ㅎㅎ",
	" 좋은 아이디어네ㅎㅎ": " 챗봇이랑 바람나지않게 조심해야겠다ㅋㅋ",
	" 챗봇이랑 바람나지않게 조심해야겠다ㅋㅋ": " 채팅로그.csv",
	" 채팅로그.csv": " 42 바이트"
}